MANIFEST.in
requirements.txt
setup.cfg
setup.py
toolkit/__init__.py
toolkit/async_context.py
toolkit/singleton.py
toolkit/components/__init__.py
toolkit/components/multi_worker.py
toolkit/components/processor.py
toolkit/service/__init__.py
toolkit/service/combine.py
toolkit/service/console.py
toolkit/service/monitors.py
toolkit/service/plugins.py
toolkit/settings/__init__.py
toolkit/settings/frozen.py
toolkit/settings/settings.py
toolkit/structures/__init__.py
toolkit/structures/linked_list.py
toolkit/structures/queues.py
toolkit/structures/thread_safe_collections.py
toolkit/tools/__init__.py
toolkit/tools/file_buffalo.py
toolkit/tools/github-markdown.css
toolkit/tools/managers.py
toolkit/tools/markdown_helper.py
toolkit/tools/package_control.py
toolkit/tools/redis_tools.py
toolkit/translator/__init__.py
toolkit/translator/sites.py
toolkit/translator/token_acquirer.py
toolkit/translator/translate_adapter.py
toolkity.egg-info/PKG-INFO
toolkity.egg-info/SOURCES.txt
toolkity.egg-info/dependency_links.txt
toolkity.egg-info/entry_points.txt
toolkity.egg-info/requires.txt
toolkity.egg-info/top_level.txt
toolkity.egg-info/zip-safe