Metadata-Version: 1.1
Name: toolkity
Version: 1.9.1
Summary: simple function tools. 
Home-page: https://www.github.com/ShichaoMa/toolkit
Author: cn
Author-email: cnaafhvk@foxmail.com
License: MIT
Keywords: tools function
Platform: UNKNOWN
Classifier: License :: OSI Approved :: MIT License
Classifier: Programming Language :: Python
Classifier: Intended Audience :: Developers
Classifier: Operating System :: OS Independent
